{
  "id": "DataIngestionStrategy",
  "namespace": "Systemorph/Marketing",
  "name": "Data Ingestion Strategy",
  "nodeType": "Markdown",
  "category": "Platform",
  "description": "Two distinct modes of ingestion: historic and real-time",
  "icon": "/static/content/Systemorph/Marketing/icons/arrow-download.svg",
  "displayOrder": 20,
  "addressSegments": 0,
  "isPersistent": true,
  "content": {
    "$type": "MarkdownDocument",
    "id": "DataIngestionStrategy",
    "title": "Data Ingestion Strategy",
    "iconName": "Document",
    "content": "# Data Ingestion Strategy\n\n## Two Distinct Modes of Ingestion\n\nData ingestion for AI-driven workflows must address two fundamentally different scenarios: processing historic data that already exists in repositories, and handling new information as it arrives in real-time.\n\n| Mode | Purpose | Approach | Volume | Human Role |\n|------|---------|----------|--------|------------|\n| **Historic** | Reverse-engineer connections from existing data | Batch processing with human validation | One-time, high volume | Review and confirm relationships |\n| **Real-Time** | Process incoming work as it arrives | Event-driven, collaborative | Continuous, lower volume | Complete submissions with agent assistance |\n\n## Historic Data Ingestion: Reverse-Engineering the Data Mesh\n\nDocument repositories contain years of accumulated documents—emails, PDFs, scanned images, Word documents, and spreadsheets. Historic ingestion is essentially a **reverse-engineering exercise**: starting from scattered artifacts and structured databases, we work backwards to discover and establish the connections.\n\n## Real-Time Ingestion: Collaborative Processing\n\nIn everyday Middle Office work, most new information arrives via email. The key distinction from historic ingestion is that **the user is an active participant**, not just a validator.\n\n### Email Integration Options\n\n1. **Dedicated Mailbox Monitoring**: A dedicated mailbox receives incoming communications with AI agent monitoring\n2. **Outlook Plugin**: Users process emails from their own inboxes using an Outlook plugin\n\n## Building the Annotated Data Model\n\nCurrent flagship AI models are remarkably capable at following instructions. **The bottleneck is not model capability—it's getting the right context into the model's working memory.**\n\nA properly annotated data model provides:\n- **Entity definitions**: What is a Submission? What is a Layer?\n- **Field descriptions**: What each field means and how to identify it\n- **Dimension values**: Detailed descriptions of valid values\n- **Business rules**: Validation logic in natural language\n\n## Summary\n\nEffective data ingestion for AI requires:\n\n1. **Two distinct modes**: Historic reverse-engineering and real-time collaborative processing\n2. **Human-in-the-loop collaboration**: Neither mode is fully automated\n3. **Content preparation**: All media types converted to textual descriptions\n4. **Annotated data models**: Natural language descriptions enable accurate AI mapping\n5. **File format instructions**: Specific guidance for each format type\n6. **Everything as addressable data**: Agent definitions and instructions are data items\n7. **Addressability as foundation**: The key to successful AI processing"
  }
}
