{
  "id": "Article",
  "namespace": "ACME",
  "name": "Article",
  "nodeType": "NodeType",
  "category": "Types",
  "description": "An Software content article with metadata",
  "icon": "/static/NodeTypeIcons/document.svg",
  "isPersistent": true,
  "content": {
    "$type": "NodeTypeDefinition",
    "id": "Article",
    "namespace": "ACME",
    "displayName": "Article",
    "iconName": "DocumentText",
    "description": "An Software content article with metadata",
    "configuration": "config => config.WithContentType<Article>().AddDefaultLayoutAreas().AddLayout(layout => layout.WithDefaultArea(\"Overview\").AddArticleViews())"
  }
}
