{"$type":"MeshNode","id":"Product","namespace":"Northwind","path":"Northwind/Product","mainNode":"Northwind/Product","name":"Product","description":"Product master data with inventory and pricing information","nodeType":"NodeType","category":"Types","icon":"/static/NodeTypeIcons/shopping-bag.svg","lastModified":"2026-06-26T10:47:30.878102+00:00","lastModifiedBy":"system-security","version":7,"state":"Active","content":{"$type":"NodeTypeDefinition","description":"Product master data with inventory and pricing information","configuration":"config =\u003E config.WithContentType\u003CProductContent\u003E().AddDefaultLayoutAreas().AddLayout(layout =\u003E layout.AddProductNodeLayoutAreas())","showChildrenInDetails":true,"detailsChildrenLimit":10,"includeGlobalTypes":true,"compilationStatus":"Error","compilationError":"Compilation failed: Compilation failed for \u0027Northwind/Product\u0027:\nCS0246 Error (line 200): The type or namespace name \u0027Supplier\u0027 could not be found (are you missing a using directive or an assembly reference?)\nCS0246 Error (line 204): The type or namespace name \u0027Category\u0027 could not be found (are you missing a using directive or an assembly reference?)\nCS0105 Warning (line 27): The using directive for \u0027System.Reactive.Linq\u0027 appeared previously in this namespace\nCS0105 Warning (line 29): The using directive for \u0027MeshWeaver.Domain\u0027 appeared previously in this namespace\nCS0105 Warning (line 30): The using directive for \u0027MeshWeaver.Layout\u0027 appeared previously in this namespace\nCS0105 Warning (line 31): The using directive for \u0027System.ComponentModel\u0027 appeared previously in this namespace\nCS0105 Warning (line 32): The using directive for \u0027System.ComponentModel.DataAnnotations\u0027 appeared previously in this namespace\nCS0105 Warning (line 33): The using directive for \u0027MeshWeaver.Domain\u0027 appeared previously in this namespace\nCS8632 Warning (line 51): The annotation for nullable reference types should only be used in code within a \u0027#nullable\u0027 annotations context.\nCS8632 Warning (line 51): The annotation for nullable reference types should only be used in code within a \u0027#nullable\u0027 annotations context.\nCS8632 Warning (line 80): The annotation for nullable reference types should only be used in code within a \u0027#nullable\u0027 annotations context.\nCS8632 Warning (line 137): The annotation for nullable reference types should only be used in code within a \u0027#nullable\u0027 annotations context.\nCS1701 Warning: Assuming assembly reference \u0027System.Linq.Expressions, Version=6.0.0.0, Culture=neutral, PublicKeyToken=b03f5f7f11d50a3a\u0027 used by \u0027System.Reactive\u0027 matches identity \u0027System.Linq.Expressions, Version=10.0.0.0, Culture=neutral, PublicKeyToken=b03f5f7f11d50a3a\u0027 of \u0027System.Linq.Expressions\u0027, you may need to supply runtime policy\nCS1701 Warning: Assuming assembly reference \u0027System.Linq.Expressions, Version=6.0.0.0, Culture=neutral, PublicKeyToken=b03f5f7f11d50a3a\u0027 used by \u0027System.Reactive\u0027 matches identity \u0027System.Linq.Expressions, Version=10.0.0.0, Culture=neutral, PublicKeyToken=b03f5f7f11d50a3a\u0027 of \u0027System.Linq.Expressions\u0027, you may need to supply runtime policy\nCS8632 Warning (line 93): The annotation for nullable reference types should only be used in code within a \u0027#nullable\u0027 annotations context.\nCS8632 Warning (line 99): The annotation for nullable reference types should only be used in code within a \u0027#nullable\u0027 annotations context.\nCS1701 Warning: Assuming assembly reference \u0027System.Linq.Expressions, Version=6.0.0.0, Culture=neutral, PublicKeyToken=b03f5f7f11d50a3a\u0027 used by \u0027System.Reactive\u0027 matches identity \u0027System.Linq.Expressions, Version=10.0.0.0, Culture=neutral, PublicKeyToken=b03f5f7f11d50a3a\u0027 of \u0027System.Linq.Expressions\u0027, you may need to supply runtime policy\nCS1701 Warning: Assuming assembly reference \u0027System.Linq.Expressions, Version=6.0.0.0, Culture=neutral, PublicKeyToken=b03f5f7f11d50a3a\u0027 used by \u0027System.Reactive\u0027 matches identity \u0027System.Linq.Expressions, Version=10.0.0.0, Culture=neutral, PublicKeyToken=b03f5f7f11d50a3a\u0027 of \u0027System.Linq.Expressions\u0027, you may need to supply runtime policy\nCS8632 Warning (line 150): The annotation for nullable reference types should only be used in code within a \u0027#nullable\u0027 annotations context.\nCS8632 Warning (line 159): The annotation for nullable reference types should only be used in code within a \u0027#nullable\u0027 annotations context.\nCS1591 Warning (line 45): Missing XML comment for publicly visible type or member \u0027ProductNodeLayoutAreas.AddProductNodeLayoutAreas(LayoutDefinition)\u0027\nCS1591 Warning (line 193): Missing XML comment for publicly visible type or member \u0027ProductContent.ProductId\u0027\nCS1591 Warning (line 197): Missing XML comment for publicly visible type or member \u0027ProductContent.ProductName\u0027\nCS1591 Warning (line 201): Missing XML comment for publicly visible type or member \u0027ProductContent.SupplierId\u0027\nCS1591 Warning (line 205): Missing XML comment for publicly visible type or member \u0027ProductContent.CategoryId\u0027\nCS1591 Warning (line 207): Missing XML comment for publicly visible type or member \u0027ProductContent.QuantityPerUnit\u0027\nCS1591 Warning (line 210): Missing XML comment for publicly visible type or member \u0027ProductContent.UnitPrice\u0027\nCS1591 Warning (line 212): Missing XML comment for publicly visible type or member \u0027ProductContent.UnitsInStock\u0027\nCS1591 Warning (line 214): Missing XML comment for publicly visible type or member \u0027ProductContent.UnitsOnOrder\u0027\nCS1591 Warning (line 216): Missing XML comment for publicly visible type or member \u0027ProductContent.ReorderLevel\u0027\nCS1591 Warning (line 218): Missing XML comment for publicly visible type or member \u0027ProductContent.Discontinued\u0027\nCS1591 Warning (line 223): Missing XML comment for publicly visible type or member \u0027Northwind_ProductMeshNodeProviderAttribute\u0027\nCS1591 Warning (line 225): Missing XML comment for publicly visible type or member \u0027Northwind_ProductMeshNodeProviderAttribute.Nodes\u0027\n--- Source discovery ---\nExecuted source queries (2):\n  - namespace:Northwind/Product/Source scope:subtree nodeType:Code\n  - namespace:Northwind/Product/Test scope:subtree nodeType:Code\nMatched Code nodes (2):\n  - Northwind/Product/Source/ProductNodeLayoutAreas\n  - Northwind/Product/Source/ProductContent\n","compilationDiagnostics":[{"id":"CS0103","severity":"Error","message":"The name \u0027MeshNode\u0027 does not exist in the current context","location":{"sourcePath":"Northwind/Product/Source/ProductContent","range":{"start":{"line":13,"character":29},"end":{"line":13,"character":37}}}},{"id":"CS0246","severity":"Error","message":"The type or namespace name \u0027Supplier\u0027 could not be found (are you missing a using directive or an assembly reference?)","location":{"sourcePath":"Northwind/Product/Source/ProductContent","range":{"start":{"line":17,"character":22},"end":{"line":17,"character":30}}}},{"id":"CS0246","severity":"Error","message":"The type or namespace name \u0027Category\u0027 could not be found (are you missing a using directive or an assembly reference?)","location":{"sourcePath":"Northwind/Product/Source/ProductContent","range":{"start":{"line":21,"character":22},"end":{"line":21,"character":30}}}},{"id":"CS0246","severity":"Error","message":"The type or namespace name \u0027LayoutDefinition\u0027 could not be found (are you missing a using directive or an assembly reference?)","location":{"sourcePath":"Northwind/Product/Source/ProductNodeLayoutAreas","range":{"start":{"line":11,"character":66},"end":{"line":11,"character":82}}}},{"id":"CS0246","severity":"Error","message":"The type or namespace name \u0027LayoutDefinition\u0027 could not be found (are you missing a using directive or an assembly reference?)","location":{"sourcePath":"Northwind/Product/Source/ProductNodeLayoutAreas","range":{"start":{"line":11,"character":18},"end":{"line":11,"character":34}}}},{"id":"CS0246","severity":"Error","message":"The type or namespace name \u0027MeshNode\u0027 could not be found (are you missing a using directive or an assembly reference?)","location":{"sourcePath":"Northwind/Product/Source/ProductNodeLayoutAreas","range":{"start":{"line":17,"character":57},"end":{"line":17,"character":65}}}},{"id":"CS1061","severity":"Error","message":"\u0027MeshNode?\u0027 does not contain a definition for \u0027Content\u0027 and no accessible extension method \u0027Content\u0027 accepting a first argument of type \u0027MeshNode?\u0027 could be found (are you missing a using directive or an assembly reference?)","location":{"sourcePath":"Northwind/Product/Source/ProductNodeLayoutAreas","range":{"start":{"line":22,"character":17},"end":{"line":22,"character":24}}}},{"id":"CS1061","severity":"Error","message":"\u0027MeshNode?\u0027 does not contain a definition for \u0027Content\u0027 and no accessible extension method \u0027Content\u0027 accepting a first argument of type \u0027MeshNode?\u0027 could be found (are you missing a using directive or an assembly reference?)","location":{"sourcePath":"Northwind/Product/Source/ProductNodeLayoutAreas","range":{"start":{"line":25,"character":17},"end":{"line":25,"character":24}}}},{"id":"CS0616","severity":"Error","message":"\u0027Display\u0027 is not an attribute class","location":{"sourcePath":"Northwind/Product/Source/ProductNodeLayoutAreas","range":{"start":{"line":45,"character":5},"end":{"line":45,"character":12}}}},{"id":"CS0246","severity":"Error","message":"The type or namespace name \u0027GroupName\u0027 could not be found (are you missing a using directive or an assembly reference?)","location":{"sourcePath":"Northwind/Product/Source/ProductNodeLayoutAreas","range":{"start":{"line":45,"character":13},"end":{"line":45,"character":22}}}},{"id":"CS0246","severity":"Error","message":"The type or namespace name \u0027Order\u0027 could not be found (are you missing a using directive or an assembly reference?)","location":{"sourcePath":"Northwind/Product/Source/ProductNodeLayoutAreas","range":{"start":{"line":45,"character":37},"end":{"line":45,"character":42}}}},{"id":"CS0246","severity":"Error","message":"The type or namespace name \u0027LayoutAreaHost\u0027 could not be found (are you missing a using directive or an assembly reference?)","location":{"sourcePath":"Northwind/Product/Source/ProductNodeLayoutAreas","range":{"start":{"line":46,"character":58},"end":{"line":46,"character":72}}}},{"id":"CS0246","severity":"Error","message":"The type or namespace name \u0027RenderingContext\u0027 could not be found (are you missing a using directive or an assembly reference?)","location":{"sourcePath":"Northwind/Product/Source/ProductNodeLayoutAreas","range":{"start":{"line":46,"character":79},"end":{"line":46,"character":95}}}},{"id":"CS0246","severity":"Error","message":"The type or namespace name \u0027IObservable\u003C\u003E\u0027 could not be found (are you missing a using directive or an assembly reference?)","location":{"sourcePath":"Northwind/Product/Source/ProductNodeLayoutAreas","range":{"start":{"line":46,"character":18},"end":{"line":46,"character":41}}}},{"id":"CS0246","severity":"Error","message":"The type or namespace name \u0027MeshNode\u0027 could not be found (are you missing a using directive or an assembly reference?)","location":{"sourcePath":"Northwind/Product/Source/ProductNodeLayoutAreas","range":{"start":{"line":50,"character":50},"end":{"line":50,"character":58}}}},{"id":"CS0103","severity":"Error","message":"The name \u0027Array\u0027 does not exist in the current context","location":{"sourcePath":"Northwind/Product/Source/ProductNodeLayoutAreas","range":{"start":{"line":50,"character":88},"end":{"line":50,"character":93}}}},{"id":"CS0246","severity":"Error","message":"The type or namespace name \u0027MeshNode\u0027 could not be found (are you missing a using directive or an assembly reference?)","location":{"sourcePath":"Northwind/Product/Source/ProductNodeLayoutAreas","range":{"start":{"line":50,"character":100},"end":{"line":50,"character":108}}}},{"id":"CS0103","severity":"Error","message":"The name \u0027Array\u0027 does not exist in the current context","location":{"sourcePath":"Northwind/Product/Source/ProductNodeLayoutAreas","range":{"start":{"line":51,"character":33},"end":{"line":51,"character":38}}}},{"id":"CS0246","severity":"Error","message":"The type or namespace name \u0027MeshNode\u0027 could not be found (are you missing a using directive or an assembly reference?)","location":{"sourcePath":"Northwind/Product/Source/ProductNodeLayoutAreas","range":{"start":{"line":51,"character":45},"end":{"line":51,"character":53}}}},{"id":"CS0616","severity":"Error","message":"\u0027Display\u0027 is not an attribute class","location":{"sourcePath":"Northwind/Product/Source/ProductNodeLayoutAreas","range":{"start":{"line":102,"character":5},"end":{"line":102,"character":12}}}},{"id":"CS0246","severity":"Error","message":"The type or namespace name \u0027GroupName\u0027 could not be found (are you missing a using directive or an assembly reference?)","location":{"sourcePath":"Northwind/Product/Source/ProductNodeLayoutAreas","range":{"start":{"line":102,"character":13},"end":{"line":102,"character":22}}}},{"id":"CS0246","severity":"Error","message":"The type or namespace name \u0027Order\u0027 could not be found (are you missing a using directive or an assembly reference?)","location":{"sourcePath":"Northwind/Product/Source/ProductNodeLayoutAreas","range":{"start":{"line":102,"character":38},"end":{"line":102,"character":43}}}},{"id":"CS0246","severity":"Error","message":"The type or namespace name \u0027LayoutAreaHost\u0027 could not be found (are you missing a using directive or an assembly reference?)","location":{"sourcePath":"Northwind/Product/Source/ProductNodeLayoutAreas","range":{"start":{"line":103,"character":58},"end":{"line":103,"character":72}}}},{"id":"CS0246","severity":"Error","message":"The type or namespace name \u0027RenderingContext\u0027 could not be found (are you missing a using directive or an assembly reference?)","location":{"sourcePath":"Northwind/Product/Source/ProductNodeLayoutAreas","range":{"start":{"line":103,"character":79},"end":{"line":103,"character":95}}}},{"id":"CS0246","severity":"Error","message":"The type or namespace name \u0027IObservable\u003C\u003E\u0027 could not be found (are you missing a using directive or an assembly reference?)","location":{"sourcePath":"Northwind/Product/Source/ProductNodeLayoutAreas","range":{"start":{"line":103,"character":18},"end":{"line":103,"character":41}}}},{"id":"CS0246","severity":"Error","message":"The type or namespace name \u0027MeshNode\u0027 could not be found (are you missing a using directive or an assembly reference?)","location":{"sourcePath":"Northwind/Product/Source/ProductNodeLayoutAreas","range":{"start":{"line":107,"character":50},"end":{"line":107,"character":58}}}},{"id":"CS0103","severity":"Error","message":"The name \u0027Array\u0027 does not exist in the current context","location":{"sourcePath":"Northwind/Product/Source/ProductNodeLayoutAreas","range":{"start":{"line":107,"character":88},"end":{"line":107,"character":93}}}},{"id":"CS0246","severity":"Error","message":"The type or namespace name \u0027MeshNode\u0027 could not be found (are you missing a using directive or an assembly reference?)","location":{"sourcePath":"Northwind/Product/Source/ProductNodeLayoutAreas","range":{"start":{"line":107,"character":100},"end":{"line":107,"character":108}}}},{"id":"CS0103","severity":"Error","message":"The name \u0027Array\u0027 does not exist in the current context","location":{"sourcePath":"Northwind/Product/Source/ProductNodeLayoutAreas","range":{"start":{"line":108,"character":33},"end":{"line":108,"character":38}}}},{"id":"CS0246","severity":"Error","message":"The type or namespace name \u0027MeshNode\u0027 could not be found (are you missing a using directive or an assembly reference?)","location":{"sourcePath":"Northwind/Product/Source/ProductNodeLayoutAreas","range":{"start":{"line":108,"character":45},"end":{"line":108,"character":53}}}},{"id":"CS1701","severity":"Warning","message":"Assuming assembly reference \u0027System.Linq.Expressions, Version=6.0.0.0, Culture=neutral, PublicKeyToken=b03f5f7f11d50a3a\u0027 used by \u0027System.Reactive\u0027 matches identity \u0027System.Linq.Expressions, Version=10.0.0.0, Culture=neutral, PublicKeyToken=b03f5f7f11d50a3a\u0027 of \u0027System.Linq.Expressions\u0027, you may need to supply runtime policy"},{"id":"CS1701","severity":"Warning","message":"Assuming assembly reference \u0027System.Linq.Expressions, Version=6.0.0.0, Culture=neutral, PublicKeyToken=b03f5f7f11d50a3a\u0027 used by \u0027System.Reactive\u0027 matches identity \u0027System.Linq.Expressions, Version=10.0.0.0, Culture=neutral, PublicKeyToken=b03f5f7f11d50a3a\u0027 of \u0027System.Linq.Expressions\u0027, you may need to supply runtime policy"},{"id":"CS1591","severity":"Warning","message":"Missing XML comment for publicly visible type or member \u0027ProductContent.ProductId\u0027","location":{"sourcePath":"Northwind/Product/Source/ProductContent","range":{"start":{"line":10,"character":15},"end":{"line":10,"character":24}}}},{"id":"CS1591","severity":"Warning","message":"Missing XML comment for publicly visible type or member \u0027ProductContent.ProductName\u0027","location":{"sourcePath":"Northwind/Product/Source/ProductContent","range":{"start":{"line":14,"character":18},"end":{"line":14,"character":29}}}},{"id":"CS1591","severity":"Warning","message":"Missing XML comment for publicly visible type or member \u0027ProductContent.SupplierId\u0027","location":{"sourcePath":"Northwind/Product/Source/ProductContent","range":{"start":{"line":18,"character":15},"end":{"line":18,"character":25}}}},{"id":"CS1591","severity":"Warning","message":"Missing XML comment for publicly visible type or member \u0027ProductContent.CategoryId\u0027","location":{"sourcePath":"Northwind/Product/Source/ProductContent","range":{"start":{"line":22,"character":15},"end":{"line":22,"character":25}}}},{"id":"CS1591","severity":"Warning","message":"Missing XML comment for publicly visible type or member \u0027ProductContent.QuantityPerUnit\u0027","location":{"sourcePath":"Northwind/Product/Source/ProductContent","range":{"start":{"line":24,"character":18},"end":{"line":24,"character":33}}}},{"id":"CS1591","severity":"Warning","message":"Missing XML comment for publicly visible type or member \u0027ProductContent.UnitPrice\u0027","location":{"sourcePath":"Northwind/Product/Source/ProductContent","range":{"start":{"line":27,"character":18},"end":{"line":27,"character":27}}}},{"id":"CS1591","severity":"Warning","message":"Missing XML comment for publicly visible type or member \u0027ProductContent.UnitsInStock\u0027","location":{"sourcePath":"Northwind/Product/Source/ProductContent","range":{"start":{"line":29,"character":17},"end":{"line":29,"character":29}}}},{"id":"CS1591","severity":"Warning","message":"Missing XML comment for publicly visible type or member \u0027ProductContent.UnitsOnOrder\u0027","location":{"sourcePath":"Northwind/Product/Source/ProductContent","range":{"start":{"line":31,"character":17},"end":{"line":31,"character":29}}}},{"id":"CS1591","severity":"Warning","message":"Missing XML comment for publicly visible type or member \u0027ProductContent.ReorderLevel\u0027","location":{"sourcePath":"Northwind/Product/Source/ProductContent","range":{"start":{"line":33,"character":17},"end":{"line":33,"character":29}}}},{"id":"CS1591","severity":"Warning","message":"Missing XML comment for publicly visible type or member \u0027ProductContent.Discontinued\u0027","location":{"sourcePath":"Northwind/Product/Source/ProductContent","range":{"start":{"line":35,"character":16},"end":{"line":35,"character":28}}}},{"id":"CS1591","severity":"Warning","message":"Missing XML comment for publicly visible type or member \u0027ProductNodeLayoutAreas.AddProductNodeLayoutAreas(LayoutDefinition)\u0027","location":{"sourcePath":"Northwind/Product/Source/ProductNodeLayoutAreas","range":{"start":{"line":11,"character":35},"end":{"line":11,"character":60}}}},{"id":"CS8632","severity":"Warning","message":"The annotation for nullable reference types should only be used in code within a \u0027#nullable\u0027 annotations context.","location":{"sourcePath":"Northwind/Product/Source/ProductNodeLayoutAreas","range":{"start":{"line":17,"character":33},"end":{"line":17,"character":34}}}},{"id":"CS8632","severity":"Warning","message":"The annotation for nullable reference types should only be used in code within a \u0027#nullable\u0027 annotations context.","location":{"sourcePath":"Northwind/Product/Source/ProductNodeLayoutAreas","range":{"start":{"line":46,"character":39},"end":{"line":46,"character":40}}}},{"id":"CS8632","severity":"Warning","message":"The annotation for nullable reference types should only be used in code within a \u0027#nullable\u0027 annotations context.","location":{"sourcePath":"Northwind/Product/Source/ProductNodeLayoutAreas","range":{"start":{"line":59,"character":33},"end":{"line":59,"character":34}}}},{"id":"CS8632","severity":"Warning","message":"The annotation for nullable reference types should only be used in code within a \u0027#nullable\u0027 annotations context.","location":{"sourcePath":"Northwind/Product/Source/ProductNodeLayoutAreas","range":{"start":{"line":65,"character":29},"end":{"line":65,"character":30}}}},{"id":"CS8632","severity":"Warning","message":"The annotation for nullable reference types should only be used in code within a \u0027#nullable\u0027 annotations context.","location":{"sourcePath":"Northwind/Product/Source/ProductNodeLayoutAreas","range":{"start":{"line":103,"character":39},"end":{"line":103,"character":40}}}},{"id":"CS8632","severity":"Warning","message":"The annotation for nullable reference types should only be used in code within a \u0027#nullable\u0027 annotations context.","location":{"sourcePath":"Northwind/Product/Source/ProductNodeLayoutAreas","range":{"start":{"line":116,"character":33},"end":{"line":116,"character":34}}}},{"id":"CS8632","severity":"Warning","message":"The annotation for nullable reference types should only be used in code within a \u0027#nullable\u0027 annotations context.","location":{"sourcePath":"Northwind/Product/Source/ProductNodeLayoutAreas","range":{"start":{"line":125,"character":29},"end":{"line":125,"character":30}}}}],"lastCompileStartedAt":"2026-06-26T10:47:30.932018\u002B00:00","lastCompilationActivityPath":"Northwind/Product/_Activity/compile-202606261047309072287eab6a9d04f97af216589dba4376a","requestedReleaseAt":"2026-06-26T10:47:30.877705\u002B00:00","lastReleaseRequestHandledAt":"2026-06-26T10:47:30.877705\u002B00:00","currentSourceVersions":{"Northwind/Product/Source/ProductContent":639178326432906872,"Northwind/Product/Source/ProductNodeLayoutAreas":639178326432907527}}}