{
  "id": "BSBEV",
  "namespace": "Northwind/Customer",
  "name": "B's Beverages",
  "nodeType": "Northwind/Customer",
  "category": "Customers",
  "description": "B's Beverages - London, UK",
  "iconName": "Users",
  "isPersistent": true,
  "content": {
    "$type": "CustomerContent",
    "customerId": "BSBEV",
    "companyName": "B's Beverages",
    "contactName": "Victoria Ashworth",
    "contactTitle": "Sales Representative",
    "city": "London",
    "region": "",
    "postalCode": "EC2 5NT",
    "country": "UK",
    "phone": "(171) 555-1212",
    "fax": ""
  }
}