{"$type":"MeshNode","id":"Pricing","namespace":"Cornerstone","path":"Cornerstone/Pricing","mainNode":"Cornerstone/Pricing","name":"Pricing","description":"Cornerstone pricing with property risks and reinsurance structure","nodeType":"NodeType","category":"Types","icon":"/static/storage/content/Cornerstone/icons/pricing.svg","lastModified":"2026-06-26T09:24:11.080473+00:00","lastModifiedBy":"system-security","version":10,"state":"Active","content":{"$type":"NodeTypeDefinition","description":"Cornerstone pricing with property risks and reinsurance structure","configuration":"config =\u003E config.WithContentType\u003CPricing\u003E().AddContentCollection(sp =\u003E { var hub = sp.GetRequiredService\u003CIMessageHub\u003E(); var pricingId = hub.Address.Id; var basePath = System.IO.Path.Combine(\u0022../../samples/Graph/attachments/Cornerstone\u0022, hub.Address.Segments[1], hub.Address.Segments[2], \u0022Submissions\u0022); return new ContentCollectionConfig { SourceType = FileSystemStreamProvider.SourceType, Name = $\u0022Submissions@{pricingId}\u0022, BasePath = basePath, DisplayName = \u0022Submission Files\u0022 }; }).AddData(data =\u003E data.AddSource(source =\u003E { var hub = source.Workspace.Hub; var pricingId = hub.Address.Id; var insuredName = hub.Address.Segments[1]; var isMicrosoft = insuredName == \u0022Microsoft\u0022; return source.WithType\u003CLineOfBusiness\u003E(t =\u003E t.WithInitialData(LineOfBusiness.All)).WithType\u003CCountry\u003E(t =\u003E t.WithInitialData(Country.All)).WithType\u003CCurrency\u003E(t =\u003E t.WithInitialData(Currency.All)).WithType\u003CLegalEntity\u003E(t =\u003E t.WithInitialData(LegalEntity.All)).WithType\u003CPricingStatus\u003E(t =\u003E t.WithInitialData(PricingStatus.All)).WithType\u003CPropertyRisk\u003E(t =\u003E isMicrosoft ? t.WithInitialData(() =\u003E MicrosoftDataLoader.LoadPropertyRisks(hub)) : t.WithInitialData(Array.Empty\u003CPropertyRisk\u003E())).WithType\u003CReinsuranceAcceptance\u003E(t =\u003E isMicrosoft ? t.WithInitialData(() =\u003E MicrosoftDataLoader.LoadReinsuranceAcceptances(hub, pricingId)) : t.WithInitialData(Array.Empty\u003CReinsuranceAcceptance\u003E())).WithType\u003CReinsuranceSection\u003E(t =\u003E isMicrosoft ? t.WithInitialData(() =\u003E MicrosoftDataLoader.LoadReinsuranceSections(hub, pricingId)) : t.WithInitialData(Array.Empty\u003CReinsuranceSection\u003E())).WithType\u003CExcelImportConfiguration\u003E(t =\u003E t.WithInitialData(isMicrosoft ? MicrosoftSampleData.ImportConfigs : Array.Empty\u003CExcelImportConfiguration\u003E())); })).AddDefaultLayoutAreas().AddLayout(layout =\u003E layout.WithDefaultArea(\u0022Overview\u0022).AddPricingLayoutAreas())","showChildrenInDetails":true,"detailsChildrenLimit":10,"includeGlobalTypes":true,"compilationStatus":"Ok","lastCompileStartedAt":"2026-06-26T09:24:12.520758\u002B00:00","lastCompileSucceededAt":"2026-06-26T09:24:12.557278\u002B00:00","lastCompiledVersion":9,"lastCompilationActivityPath":"Cornerstone/Pricing/_Activity/compile-2026062609241247984abc68138a84e24828d6dfddcee7801","latestReleasePath":"Cornerstone/Pricing/Release/20260626092412-v6gZJkpU","requestedReleaseAt":"2026-06-26T09:24:11.080435\u002B00:00","lastReleaseRequestHandledAt":"2026-06-26T09:24:11.080435\u002B00:00","latestAssemblyCollection":"local","latestAssemblyPath":"Cornerstone_Pricing/v9-fe2dc96f-ed16b9c5c983.dll","compiledSources":{"Cornerstone/Pricing/Source/MicrosoftSampleData":639178326432858688,"Cornerstone/Pricing/Source/Currency":639178326432856094,"Cornerstone/Pricing/Source/PricingLayoutAreas":639178326432859956,"Cornerstone/Pricing/Source/PricingStatus":639178326432860545,"Cornerstone/Pricing/Source/MicrosoftDataLoader":639178326432858100,"Cornerstone/Pricing/Source/ReinsuranceSection":639178326432861968,"Cornerstone/Pricing/Source/Pricing":639178326432859226,"Cornerstone/Pricing/Source/Country":639178326432855416,"Cornerstone/Pricing/Source/LineOfBusiness":639178326432857378,"Cornerstone/Pricing/Source/ReinsuranceAcceptance":639178326432861521,"Cornerstone/Pricing/Source/PropertyRisk":639178326432861049,"Cornerstone/Pricing/Source/SlipParser":639178326432862568,"Cornerstone/Pricing/Source/LegalEntity":639178326432856662},"currentSourceVersions":{"Cornerstone/Pricing/Source/MicrosoftSampleData":639178326432858688,"Cornerstone/Pricing/Source/Currency":639178326432856094,"Cornerstone/Pricing/Source/PricingLayoutAreas":639178326432859956,"Cornerstone/Pricing/Source/PricingStatus":639178326432860545,"Cornerstone/Pricing/Source/MicrosoftDataLoader":639178326432858100,"Cornerstone/Pricing/Source/ReinsuranceSection":639178326432861968,"Cornerstone/Pricing/Source/Pricing":639178326432859226,"Cornerstone/Pricing/Source/Country":639178326432855416,"Cornerstone/Pricing/Source/LineOfBusiness":639178326432857378,"Cornerstone/Pricing/Source/ReinsuranceAcceptance":639178326432861521,"Cornerstone/Pricing/Source/PropertyRisk":639178326432861049,"Cornerstone/Pricing/Source/SlipParser":639178326432862568,"Cornerstone/Pricing/Source/LegalEntity":639178326432856662},"compiledFrameworkVersion":"fe2dc96f9e4c4436aeb04a8b645c76db"}}